httomolibgpu/__init__.py
httomolibgpu/cupywrapper.py
httomolibgpu/memory_estimator_helpers.py
httomolibgpu/cuda_kernels/__init__.py
httomolibgpu/cuda_kernels/calc_metrics.cu
httomolibgpu/cuda_kernels/center_360_shifts.cu
httomolibgpu/cuda_kernels/generate_mask.cu
httomolibgpu/cuda_kernels/median_kernel.cu
httomolibgpu/cuda_kernels/raven_filter.cu
httomolibgpu/cuda_kernels/remove_nan_inf.cu
httomolibgpu/cuda_kernels/remove_stripe_fw.cu
httomolibgpu/misc/__init__.py
httomolibgpu/misc/corr.py
httomolibgpu/misc/denoise.py
httomolibgpu/misc/morph.py
httomolibgpu/misc/rescale.py
httomolibgpu/misc/utils.py
httomolibgpu/prep/__init__.py
httomolibgpu/prep/alignment.py
httomolibgpu/prep/normalize.py
httomolibgpu/prep/phase.py
httomolibgpu/prep/stripe.py
httomolibgpu/recon/__init__.py
httomolibgpu/recon/_phase_cross_correlation.py
httomolibgpu/recon/algorithm.py
httomolibgpu/recon/rotation.py
httomolibgpu-5.3.dist-info/licenses/LICENSE
httomolibgpu-5.3.dist-info/METADATA
httomolibgpu-5.3.dist-info/WHEEL
httomolibgpu-5.3.dist-info/top_level.txt
httomolibgpu-5.3.dist-info/RECORD
