Metadata-Version: 2.4
Name: httomolibgpu
Version: 5.3
Summary: Commonly used tomography data processing methods at DLS.
Author-email: Daniil Kazantsev <daniil.kazantsev@diamond.ac.uk>, Yousef Moazzam <yousef.moazzam@diamond.ac.uk>, Naman Gera <naman.gera@diamond.ac.uk>
License: BSD-3-Clause
Project-URL: Repository, https://github.com/DiamondLightSource/httomolibgpu
Classifier: Development Status :: 4 - Beta
Classifier: License :: OSI Approved :: BSD License
Classifier: Programming Language :: Python :: 3.10
Classifier: Environment :: GPU :: NVIDIA CUDA
Requires-Python: >=3.10
License-File: LICENSE
Requires-Dist: cupy==12.3.0
Requires-Dist: nvtx
Requires-Dist: numpy
Requires-Dist: scipy
Requires-Dist: pillow
Requires-Dist: scikit-image
Requires-Dist: tomobar
Requires-Dist: PyWavelets
Provides-Extra: dev
Requires-Dist: pytest; extra == "dev"
Requires-Dist: pytest-cov; extra == "dev"
Requires-Dist: pytest-xdist; extra == "dev"
Requires-Dist: pytest-benchmark; extra == "dev"
Requires-Dist: flake8; extra == "dev"
Requires-Dist: pyproject-flake8; extra == "dev"
Requires-Dist: pydocstyle; extra == "dev"
Requires-Dist: toml; extra == "dev"
Requires-Dist: imageio; extra == "dev"
Requires-Dist: h5py; extra == "dev"
Requires-Dist: pre-commit; extra == "dev"
Requires-Dist: pyfftw; extra == "dev"
Dynamic: license-file
